nrw/__init__.py
nrw/config.yaml
nrw/nix_random_wallpaper.py
nrw-0.7.dist-info/LICENSE
nrw-0.7.dist-info/METADATA
nrw-0.7.dist-info/WHEEL
nrw-0.7.dist-info/entry_points.txt
nrw-0.7.dist-info/top_level.txt
nrw-0.7.dist-info/RECORD
