Metadata-Version: 2.1
Name: nrw
Version: 0.7
Summary: A simple program that sets random images as desktop wallpaper in *nix operating systems.
Author-email: Marcus Bowman <miliarch.mb@gmail.com>
Maintainer-email: Marcus Bowman <miliarch.mb@gmail.com>
License: MIT License
Project-URL: Documentation, https://github.com/miliarch/nrw
Project-URL: Repository, https://github.com/miliarch/nrw.git
Keywords: gnome,cinnamon,nitrogen,linux,random,wallpaper,desktop,background,unsplash
Requires-Python: >=3.7
License-File: LICENSE
Requires-Dist: Pillow >=9.4.0
Requires-Dist: PyYAML >=5.4.1
Requires-Dist: requests >=2.26.0
